dicordnum/__init__.py
dicordnum-1.4.1.dist-info/LICENSE
dicordnum-1.4.1.dist-info/METADATA
dicordnum-1.4.1.dist-info/WHEEL
dicordnum-1.4.1.dist-info/top_level.txt
dicordnum-1.4.1.dist-info/RECORD
