Metadata-Version: 2.1
Name: dicordnum
Version: 1.4.1
Summary: Dictionary ordinal number notation package
Home-page: https://github.com/muzudho/dictionary-ordinal-number-notation
Author: muzudho
Author-email: muzudho1@gmail.com
Project-URL: Bug Tracker, https://github.com/muzudho/dictionary-ordinal-number-notation/issues
Classifier: Programming Language :: Python :: 3
Classifier: License :: OSI Approved :: MIT License
Classifier: Operating System :: OS Independent
Requires-Python: >=3.6
License-File: LICENSE
